MANIFEST.in
README.md
setup.py
swagger_react_admin_generator/__init__.py
swagger_react_admin_generator/generator.py
swagger_react_admin_generator.egg-info/PKG-INFO
swagger_react_admin_generator.egg-info/SOURCES.txt
swagger_react_admin_generator.egg-info/dependency_links.txt
swagger_react_admin_generator.egg-info/not-zip-safe
swagger_react_admin_generator.egg-info/requires.txt
swagger_react_admin_generator.egg-info/top_level.txt
swagger_react_admin_generator/templates/DateRangeInput.js
swagger_react_admin_generator/templates/DateTimeInput.js
swagger_react_admin_generator/templates/EditToolbar.js
swagger_react_admin_generator/templates/EditToolbar_permissions.js
swagger_react_admin_generator/templates/EmptyField.js
swagger_react_admin_generator/templates/Filters.js
swagger_react_admin_generator/templates/ListActions.js
swagger_react_admin_generator/templates/ListActions_permissions.js
swagger_react_admin_generator/templates/Menu.js
swagger_react_admin_generator/templates/MyLayout.js
swagger_react_admin_generator/templates/NoPermissions.js
swagger_react_admin_generator/templates/ObjectField.js
swagger_react_admin_generator/templates/PermissionsStore.js
swagger_react_admin_generator/templates/ReactAdmin.js
swagger_react_admin_generator/templates/ReactAdmin_permissions.js
swagger_react_admin_generator/templates/Resource.js
swagger_react_admin_generator/templates/Resource_permissions.js
swagger_react_admin_generator/templates/authProvider.js
swagger_react_admin_generator/templates/catchAll.js
swagger_react_admin_generator/templates/customRoutes.js
swagger_react_admin_generator/templates/dataProvider.js
swagger_react_admin_generator/templates/theme.js
swagger_react_admin_generator/templates/utils.js