Metadata-Version: 1.1
Name: swagger-react-admin-generator
Version: 0.1.6
Summary: Python React Admin Generator using a Swagger Specification.
Home-page: UNKNOWN
Author: David Oberholzer
Author-email: davidobework@gmail.com
License: MIT
Platform: UNKNOWN
Classifier: Programming Language :: Python
Classifier: License :: OSI Approved :: MIT License
Classifier: Operating System :: OS Independent
Classifier: Intended Audience :: Developers
Classifier: Topic :: Internet :: WWW/HTTP :: Dynamic Content
Classifier: Programming Language :: Python :: 3.6
Classifier: Programming Language :: Python :: 3.7
